wavevid/__init__.py
wavevid/animations.py
wavevid/audio.py
wavevid/backgrounds.py
wavevid/cli.py
wavevid/generate_end_screen.py
wavevid/renderer.py
wavevid/transcribe.py
wavevid/backgrounds/bg1.jpg
wavevid/backgrounds/bg10.jpg
wavevid/backgrounds/bg2.jpg
wavevid/backgrounds/bg3.jpg
wavevid/backgrounds/bg4.jpg
wavevid/backgrounds/bg5.jpg
wavevid/backgrounds/bg6.jpg
wavevid/backgrounds/bg7.jpg
wavevid/backgrounds/bg8.jpg
wavevid/backgrounds/bg9.jpg
wavevid/visualizers/__init__.py
wavevid/visualizers/bars.py
wavevid/visualizers/base.py
wavevid/visualizers/particles.py
wavevid/visualizers/radial.py
wavevid/visualizers/spectrum.py
wavevid/visualizers/waveform.py
wavevid-0.1.1.dist-info/METADATA
wavevid-0.1.1.dist-info/WHEEL
wavevid-0.1.1.dist-info/entry_points.txt
wavevid-0.1.1.dist-info/top_level.txt
wavevid-0.1.1.dist-info/RECORD
