Metadata-Version: 2.4
Name: wavevid
Version: 0.1.1
Summary: Audio to waveform video generator with subtitles
Requires-Python: >=3.10
Requires-Dist: click>=8.0
Requires-Dist: librosa>=0.10
Requires-Dist: numpy>=1.24
Requires-Dist: Pillow>=10.0
Requires-Dist: scipy>=1.10
Requires-Dist: requests>=2.28
